flask_peewee_restful/__init__.py
flask_peewee_restful/api_generator.py
flask_peewee_restful/app_generator.py
flask_peewee_restful/client.py
flask_peewee_restful/custom_fields.py
flask_peewee_restful/deserializer.py
flask_peewee_restful-1.0.9.dist-info/LICENSE
flask_peewee_restful-1.0.9.dist-info/WHEEL
flask_peewee_restful-1.0.9.dist-info/METADATA
flask_peewee_restful-1.0.9.dist-info/RECORD
