Metadata-Version: 2.1
Name: flask-peewee-restful
Version: 1.0.9
Summary: Generate Flask Restful API from Peewee Models
License: MIT
Author: Binh Vu
Author-email: binh@toan2.com
Requires-Python: >=3.8,<4.0
Classifier: License :: OSI Approved :: MIT License
Classifier: Programming Language :: Python :: 3
Classifier: Programming Language :: Python :: 3.10
Classifier: Programming Language :: Python :: 3.8
Classifier: Programming Language :: Python :: 3.9
Requires-Dist: Flask (>=2.0.2,<3.0.0)
Requires-Dist: loguru (>=0.5.3,<0.6.0)
Requires-Dist: peewee (>=3.14.4,<4.0.0)
Requires-Dist: requests (>=2.26.0,<3.0.0)
Requires-Dist: typing_extensions (>=4.0.0,<5.0.0)
